{"ast":null,"code":"import Tone from 'tone';\n\nfunction part1(synth) {\n  var part = new Tone.Part(function (time, note) {\n    console.log(time, noteName, duratiom);\n    synth.triggerAttackRelease(note.noteName, note.duration, time, note.velocity);\n  }, [{\n    time: '4n',\n    noteName: 'C2',\n    velocity: 1,\n    duration: '1n'\n  }, {\n    time: '4n',\n    noteName: 'C2',\n    velocity: 1,\n    duration: '1n'\n  }, {\n    time: '4n',\n    noteName: 'C2',\n    velocity: 1,\n    duration: '1n'\n  }, {\n    time: '4n',\n    noteName: 'D#2',\n    velocity: 1,\n    duration: '1n'\n  }, {\n    time: '4n',\n    noteName: 'F2',\n    velocity: 1,\n    duration: '1n'\n  }, {\n    time: '4n',\n    noteName: 'C2',\n    velocity: 1,\n    duration: '1n'\n  }, {\n    time: '4n',\n    noteName: 'C2',\n    velocity: 1,\n    duration: '1n'\n  }, {\n    time: '4n',\n    noteName: 'C2',\n    velocity: 1,\n    duration: '1n'\n  }, {\n    time: '4n',\n    noteName: 'C2',\n    velocity: 1,\n    duration: '1n'\n  }, {\n    time: '4n',\n    noteName: 'D#2',\n    velocity: 1,\n    duration: '1n'\n  }, {\n    time: '4n',\n    noteName: 'F2',\n    velocity: 1,\n    duration: '1n'\n  }, {\n    time: '4n',\n    noteName: 'D#2',\n    velocity: 1,\n    duration: '1n'\n  }, {\n    time: '4n',\n    noteName: 'D#2',\n    velocity: 1,\n    duration: '1n'\n  }, {\n    time: '4n',\n    noteName: 'D2',\n    velocity: 1,\n    duration: '1n'\n  }, {\n    time: '4n',\n    noteName: 'C2',\n    velocity: 1,\n    duration: '1n'\n  }, {\n    time: '4n',\n    noteName: 'C2',\n    velocity: 1,\n    duration: '1n'\n  }, {\n    time: '4n',\n    noteName: 'D#2',\n    velocity: 1,\n    duration: '1n'\n  }, {\n    time: '4n',\n    noteName: 'D2',\n    velocity: 1,\n    duration: '1n'\n  }, {\n    time: '4n',\n    noteName: 'C2',\n    velocity: 1,\n    duration: '1n'\n  }, {\n    time: '4n',\n    noteName: 'C2',\n    velocity: 1,\n    duration: '1n'\n  }]);\n  return part;\n}\n\nfunction part2(synth) {\n  var part = new Tone.Part(function (time, note) {\n    synth.triggerAttackRelease(note.noteName, note.duration, time, note.velocity);\n  }, [{\n    time: '0:0:0',\n    noteName: 'G4',\n    velocity: 1,\n    duration: '8n'\n  }, {\n    time: '0:1:0',\n    noteName: 'D4',\n    velocity: 1,\n    duration: '8n'\n  }, {\n    time: '0:2:0',\n    noteName: 'A#4',\n    velocity: 1,\n    duration: '2n'\n  }, {\n    time: '0:3:0',\n    noteName: 'G4',\n    velocity: 1,\n    duration: '8n'\n  }, {\n    time: '1:0:0',\n    noteName: 'D4',\n    velocity: 1,\n    duration: '8n'\n  }, {\n    time: '1:1:0',\n    noteName: 'A#4',\n    velocity: 1,\n    duration: '2n'\n  }, {\n    time: '1:2:0',\n    noteName: 'G4',\n    velocity: 1,\n    duration: '8n'\n  }, {\n    time: '1:3:0',\n    noteName: 'D4',\n    velocity: 1,\n    duration: '8n'\n  }, {\n    time: '0:2:0',\n    noteName: 'A#4',\n    velocity: 1,\n    duration: '2n'\n  }, {\n    time: '0:3:0',\n    noteName: 'G4',\n    velocity: 1,\n    duration: '8n'\n  }, {\n    time: '1:0:0',\n    noteName: 'D4',\n    velocity: 1,\n    duration: '8n'\n  }, {\n    time: '0:3:0',\n    noteName: 'G4',\n    velocity: 1,\n    duration: '8n'\n  }]);\n  return part;\n}\n\nexport { part1, part2 };","map":{"version":3,"sources":["/Users/bitterglaze/Share/hseadc2017_THEREMINVOX/app/javascript/components/tunes/parts.js"],"names":["Tone","part1","synth","part","Part","time","note","console","log","noteName","duratiom","triggerAttackRelease","duration","velocity","part2"],"mappings":"AAAA,OAAOA,IAAP,MAAiB,MAAjB;;AAEA,SAASC,KAAT,CAAeC,KAAf,EAAsB;AACpB,MAAIC,IAAI,GAAG,IAAIH,IAAI,CAACI,IAAT,CACT,UAASC,IAAT,EAAeC,IAAf,EAAqB;AACnBC,IAAAA,OAAO,CAACC,GAAR,CAAYH,IAAZ,EAAkBI,QAAlB,EAA4BC,QAA5B;AACAR,IAAAA,KAAK,CAACS,oBAAN,CACEL,IAAI,CAACG,QADP,EAEEH,IAAI,CAACM,QAFP,EAGEP,IAHF,EAIEC,IAAI,CAACO,QAJP;AAMD,GATQ,EAUT,CACE;AACER,IAAAA,IAAI,EAAE,IADR;AAEEI,IAAAA,QAAQ,EAAE,IAFZ;AAGEI,IAAAA,QAAQ,EAAE,CAHZ;AAIED,IAAAA,QAAQ,EAAE;AAJZ,GADF,EAOE;AACEP,IAAAA,IAAI,EAAE,IADR;AAEEI,IAAAA,QAAQ,EAAE,IAFZ;AAGEI,IAAAA,QAAQ,EAAE,CAHZ;AAIED,IAAAA,QAAQ,EAAE;AAJZ,GAPF,EAaE;AACEP,IAAAA,IAAI,EAAE,IADR;AAEEI,IAAAA,QAAQ,EAAE,IAFZ;AAGEI,IAAAA,QAAQ,EAAE,CAHZ;AAIED,IAAAA,QAAQ,EAAE;AAJZ,GAbF,EAmBE;AACEP,IAAAA,IAAI,EAAE,IADR;AAEEI,IAAAA,QAAQ,EAAE,KAFZ;AAGEI,IAAAA,QAAQ,EAAE,CAHZ;AAIED,IAAAA,QAAQ,EAAE;AAJZ,GAnBF,EAyBE;AACEP,IAAAA,IAAI,EAAE,IADR;AAEEI,IAAAA,QAAQ,EAAE,IAFZ;AAGEI,IAAAA,QAAQ,EAAE,CAHZ;AAIED,IAAAA,QAAQ,EAAE;AAJZ,GAzBF,EA+BE;AACEP,IAAAA,IAAI,EAAE,IADR;AAEEI,IAAAA,QAAQ,EAAE,IAFZ;AAGEI,IAAAA,QAAQ,EAAE,CAHZ;AAIED,IAAAA,QAAQ,EAAE;AAJZ,GA/BF,EAqCE;AACEP,IAAAA,IAAI,EAAE,IADR;AAEEI,IAAAA,QAAQ,EAAE,IAFZ;AAGEI,IAAAA,QAAQ,EAAE,CAHZ;AAIED,IAAAA,QAAQ,EAAE;AAJZ,GArCF,EA2CE;AACEP,IAAAA,IAAI,EAAE,IADR;AAEEI,IAAAA,QAAQ,EAAE,IAFZ;AAGEI,IAAAA,QAAQ,EAAE,CAHZ;AAIED,IAAAA,QAAQ,EAAE;AAJZ,GA3CF,EAiDE;AACEP,IAAAA,IAAI,EAAE,IADR;AAEEI,IAAAA,QAAQ,EAAE,IAFZ;AAGEI,IAAAA,QAAQ,EAAE,CAHZ;AAIED,IAAAA,QAAQ,EAAE;AAJZ,GAjDF,EAuDE;AACEP,IAAAA,IAAI,EAAE,IADR;AAEEI,IAAAA,QAAQ,EAAE,KAFZ;AAGEI,IAAAA,QAAQ,EAAE,CAHZ;AAIED,IAAAA,QAAQ,EAAE;AAJZ,GAvDF,EA6DE;AACEP,IAAAA,IAAI,EAAE,IADR;AAEEI,IAAAA,QAAQ,EAAE,IAFZ;AAGEI,IAAAA,QAAQ,EAAE,CAHZ;AAIED,IAAAA,QAAQ,EAAE;AAJZ,GA7DF,EAmEE;AACEP,IAAAA,IAAI,EAAE,IADR;AAEEI,IAAAA,QAAQ,EAAE,KAFZ;AAGEI,IAAAA,QAAQ,EAAE,CAHZ;AAIED,IAAAA,QAAQ,EAAE;AAJZ,GAnEF,EAyEE;AACEP,IAAAA,IAAI,EAAE,IADR;AAEEI,IAAAA,QAAQ,EAAE,KAFZ;AAGEI,IAAAA,QAAQ,EAAE,CAHZ;AAIED,IAAAA,QAAQ,EAAE;AAJZ,GAzEF,EA+EE;AACEP,IAAAA,IAAI,EAAE,IADR;AAEEI,IAAAA,QAAQ,EAAE,IAFZ;AAGEI,IAAAA,QAAQ,EAAE,CAHZ;AAIED,IAAAA,QAAQ,EAAE;AAJZ,GA/EF,EAqFE;AACEP,IAAAA,IAAI,EAAE,IADR;AAEEI,IAAAA,QAAQ,EAAE,IAFZ;AAGEI,IAAAA,QAAQ,EAAE,CAHZ;AAIED,IAAAA,QAAQ,EAAE;AAJZ,GArFF,EA2FE;AACEP,IAAAA,IAAI,EAAE,IADR;AAEEI,IAAAA,QAAQ,EAAE,IAFZ;AAGEI,IAAAA,QAAQ,EAAE,CAHZ;AAIED,IAAAA,QAAQ,EAAE;AAJZ,GA3FF,EAiGE;AACEP,IAAAA,IAAI,EAAE,IADR;AAEEI,IAAAA,QAAQ,EAAE,KAFZ;AAGEI,IAAAA,QAAQ,EAAE,CAHZ;AAIED,IAAAA,QAAQ,EAAE;AAJZ,GAjGF,EAuGE;AACEP,IAAAA,IAAI,EAAE,IADR;AAEEI,IAAAA,QAAQ,EAAE,IAFZ;AAGEI,IAAAA,QAAQ,EAAE,CAHZ;AAIED,IAAAA,QAAQ,EAAE;AAJZ,GAvGF,EA6GE;AACEP,IAAAA,IAAI,EAAE,IADR;AAEEI,IAAAA,QAAQ,EAAE,IAFZ;AAGEI,IAAAA,QAAQ,EAAE,CAHZ;AAIED,IAAAA,QAAQ,EAAE;AAJZ,GA7GF,EAmHE;AACEP,IAAAA,IAAI,EAAE,IADR;AAEEI,IAAAA,QAAQ,EAAE,IAFZ;AAGEI,IAAAA,QAAQ,EAAE,CAHZ;AAIED,IAAAA,QAAQ,EAAE;AAJZ,GAnHF,CAVS,CAAX;AAsIA,SAAOT,IAAP;AACD;;AAED,SAASW,KAAT,CAAeZ,KAAf,EAAsB;AACpB,MAAIC,IAAI,GAAG,IAAIH,IAAI,CAACI,IAAT,CACT,UAASC,IAAT,EAAeC,IAAf,EAAqB;AACnBJ,IAAAA,KAAK,CAACS,oBAAN,CACEL,IAAI,CAACG,QADP,EAEEH,IAAI,CAACM,QAFP,EAGEP,IAHF,EAIEC,IAAI,CAACO,QAJP;AAMD,GARQ,EAST,CACE;AACER,IAAAA,IAAI,EAAE,OADR;AAEEI,IAAAA,QAAQ,EAAE,IAFZ;AAGEI,IAAAA,QAAQ,EAAE,CAHZ;AAIED,IAAAA,QAAQ,EAAE;AAJZ,GADF,EAOE;AACEP,IAAAA,IAAI,EAAE,OADR;AAEEI,IAAAA,QAAQ,EAAE,IAFZ;AAGEI,IAAAA,QAAQ,EAAE,CAHZ;AAIED,IAAAA,QAAQ,EAAE;AAJZ,GAPF,EAaE;AACEP,IAAAA,IAAI,EAAE,OADR;AAEEI,IAAAA,QAAQ,EAAE,KAFZ;AAGEI,IAAAA,QAAQ,EAAE,CAHZ;AAIED,IAAAA,QAAQ,EAAE;AAJZ,GAbF,EAmBE;AACEP,IAAAA,IAAI,EAAE,OADR;AAEEI,IAAAA,QAAQ,EAAE,IAFZ;AAGEI,IAAAA,QAAQ,EAAE,CAHZ;AAIED,IAAAA,QAAQ,EAAE;AAJZ,GAnBF,EAyBE;AACEP,IAAAA,IAAI,EAAE,OADR;AAEEI,IAAAA,QAAQ,EAAE,IAFZ;AAGEI,IAAAA,QAAQ,EAAE,CAHZ;AAIED,IAAAA,QAAQ,EAAE;AAJZ,GAzBF,EA+BE;AACEP,IAAAA,IAAI,EAAE,OADR;AAEEI,IAAAA,QAAQ,EAAE,KAFZ;AAGEI,IAAAA,QAAQ,EAAE,CAHZ;AAIED,IAAAA,QAAQ,EAAE;AAJZ,GA/BF,EAqCE;AACEP,IAAAA,IAAI,EAAE,OADR;AAEEI,IAAAA,QAAQ,EAAE,IAFZ;AAGEI,IAAAA,QAAQ,EAAE,CAHZ;AAIED,IAAAA,QAAQ,EAAE;AAJZ,GArCF,EA2CE;AACEP,IAAAA,IAAI,EAAE,OADR;AAEEI,IAAAA,QAAQ,EAAE,IAFZ;AAGEI,IAAAA,QAAQ,EAAE,CAHZ;AAIED,IAAAA,QAAQ,EAAE;AAJZ,GA3CF,EAiDE;AACEP,IAAAA,IAAI,EAAE,OADR;AAEEI,IAAAA,QAAQ,EAAE,KAFZ;AAGEI,IAAAA,QAAQ,EAAE,CAHZ;AAIED,IAAAA,QAAQ,EAAE;AAJZ,GAjDF,EAuDE;AACEP,IAAAA,IAAI,EAAE,OADR;AAEEI,IAAAA,QAAQ,EAAE,IAFZ;AAGEI,IAAAA,QAAQ,EAAE,CAHZ;AAIED,IAAAA,QAAQ,EAAE;AAJZ,GAvDF,EA6DE;AACEP,IAAAA,IAAI,EAAE,OADR;AAEEI,IAAAA,QAAQ,EAAE,IAFZ;AAGEI,IAAAA,QAAQ,EAAE,CAHZ;AAIED,IAAAA,QAAQ,EAAE;AAJZ,GA7DF,EAmEE;AACEP,IAAAA,IAAI,EAAE,OADR;AAEEI,IAAAA,QAAQ,EAAE,IAFZ;AAGEI,IAAAA,QAAQ,EAAE,CAHZ;AAIED,IAAAA,QAAQ,EAAE;AAJZ,GAnEF,CATS,CAAX;AAqFA,SAAOT,IAAP;AACD;;AAED,SAASF,KAAT,EAAgBa,KAAhB","sourcesContent":["import Tone from 'tone'\n\nfunction part1(synth) {\n  let part = new Tone.Part(\n    function(time, note) {\n      console.log(time, noteName, duratiom)\n      synth.triggerAttackRelease(\n        note.noteName,\n        note.duration,\n        time,\n        note.velocity\n      )\n    },\n    [\n      {\n        time: '4n',\n        noteName: 'C2',\n        velocity: 1,\n        duration: '1n'\n      },\n      {\n        time: '4n',\n        noteName: 'C2',\n        velocity: 1,\n        duration: '1n'\n      },\n      {\n        time: '4n',\n        noteName: 'C2',\n        velocity: 1,\n        duration: '1n'\n      },\n      {\n        time: '4n',\n        noteName: 'D#2',\n        velocity: 1,\n        duration: '1n'\n      },\n      {\n        time: '4n',\n        noteName: 'F2',\n        velocity: 1,\n        duration: '1n'\n      },\n      {\n        time: '4n',\n        noteName: 'C2',\n        velocity: 1,\n        duration: '1n'\n      },\n      {\n        time: '4n',\n        noteName: 'C2',\n        velocity: 1,\n        duration: '1n'\n      },\n      {\n        time: '4n',\n        noteName: 'C2',\n        velocity: 1,\n        duration: '1n'\n      },\n      {\n        time: '4n',\n        noteName: 'C2',\n        velocity: 1,\n        duration: '1n'\n      },\n      {\n        time: '4n',\n        noteName: 'D#2',\n        velocity: 1,\n        duration: '1n'\n      },\n      {\n        time: '4n',\n        noteName: 'F2',\n        velocity: 1,\n        duration: '1n'\n      },\n      {\n        time: '4n',\n        noteName: 'D#2',\n        velocity: 1,\n        duration: '1n'\n      },\n      {\n        time: '4n',\n        noteName: 'D#2',\n        velocity: 1,\n        duration: '1n'\n      },\n      {\n        time: '4n',\n        noteName: 'D2',\n        velocity: 1,\n        duration: '1n'\n      },\n      {\n        time: '4n',\n        noteName: 'C2',\n        velocity: 1,\n        duration: '1n'\n      },\n      {\n        time: '4n',\n        noteName: 'C2',\n        velocity: 1,\n        duration: '1n'\n      },\n      {\n        time: '4n',\n        noteName: 'D#2',\n        velocity: 1,\n        duration: '1n'\n      },\n      {\n        time: '4n',\n        noteName: 'D2',\n        velocity: 1,\n        duration: '1n'\n      },\n      {\n        time: '4n',\n        noteName: 'C2',\n        velocity: 1,\n        duration: '1n'\n      },\n      {\n        time: '4n',\n        noteName: 'C2',\n        velocity: 1,\n        duration: '1n'\n      }\n    ]\n  )\n\n  return part\n}\n\nfunction part2(synth) {\n  let part = new Tone.Part(\n    function(time, note) {\n      synth.triggerAttackRelease(\n        note.noteName,\n        note.duration,\n        time,\n        note.velocity\n      )\n    },\n    [\n      {\n        time: '0:0:0',\n        noteName: 'G4',\n        velocity: 1,\n        duration: '8n'\n      },\n      {\n        time: '0:1:0',\n        noteName: 'D4',\n        velocity: 1,\n        duration: '8n'\n      },\n      {\n        time: '0:2:0',\n        noteName: 'A#4',\n        velocity: 1,\n        duration: '2n'\n      },\n      {\n        time: '0:3:0',\n        noteName: 'G4',\n        velocity: 1,\n        duration: '8n'\n      },\n      {\n        time: '1:0:0',\n        noteName: 'D4',\n        velocity: 1,\n        duration: '8n'\n      },\n      {\n        time: '1:1:0',\n        noteName: 'A#4',\n        velocity: 1,\n        duration: '2n'\n      },\n      {\n        time: '1:2:0',\n        noteName: 'G4',\n        velocity: 1,\n        duration: '8n'\n      },\n      {\n        time: '1:3:0',\n        noteName: 'D4',\n        velocity: 1,\n        duration: '8n'\n      },\n      {\n        time: '0:2:0',\n        noteName: 'A#4',\n        velocity: 1,\n        duration: '2n'\n      },\n      {\n        time: '0:3:0',\n        noteName: 'G4',\n        velocity: 1,\n        duration: '8n'\n      },\n      {\n        time: '1:0:0',\n        noteName: 'D4',\n        velocity: 1,\n        duration: '8n'\n      },\n      {\n        time: '0:3:0',\n        noteName: 'G4',\n        velocity: 1,\n        duration: '8n'\n      }\n    ]\n  )\n\n  return part\n}\n\nexport { part1, part2 }\n"]},"metadata":{},"sourceType":"module"}